<?xml version="1.0" encoding="UTF-8"?>
<prefab>
  <property name="CopyAirBlocks" value="True" />
  <property name="ExcludeDistantPOIMesh" value="False" />
  <property name="ExcludePOICulling" value="False" />
  <property name="DistantPOIYOffset" value="0" />
  <property name="AllowTopSoilDecorations" value="True" />
  <property name="DifficultyTier" value="2" />
  <property name="ShowQuestClearCount" value="1" />
  <property name="TraderArea" value="False" />
  <property name="PrefabSize" value="42, 21, 42" />
  <property name="RotationToFaceNorth" value="1" />
  <property name="YOffset" value="-1" />
  <property name="SleeperVolumeSize" value="25, 3, 15#17, 3, 9#17, 4, 9#17, 3, 9#17, 4, 9#31, 3, 40" />
  <property name="SleeperVolumeStart" value="10, 1, 1#14, 2, 17#14, 5, 17#14, 2, 30#14, 5, 30#5, 1, 1" />
  <property name="SleeperVolumeGroupId" value="0,0,0,0,0,0" />
  <property name="SleeperVolumeGroup" value="GroupZomSoldier,4,5,GroupZomSoldier,3,4,GroupZomSoldier,3,4,GroupZomSoldier,4,5,GroupZomSoldier,3,4,GroupZomSoldier,8,8" />
  <property name="SleeperIsLootVolume" value="True,True,False,True,False,False" />
  <property name="SleeperIsQuestExclude" value="False,False,False,False,False,False" />
  <property name="SleeperVolumeFlags" value="0,0,0,0,0,0" />
  <property name="SleeperVolumeTriggeredBy" value=" # # # # # " />
  <property name="Tags" value="countryresidential" />
  <property name="DuplicateRepeatDistance" value="16000" />
  <property name="EditorGroups" value="military, post_a20, tier_2, destroyed" />
  <property name="QuestTags" value="clear, fetch, infested" />
  <property name="POIMarkerSize" value="1, 13, 6" />
  <property name="POIMarkerStart" value="42, 0, 15" />
  <property name="POIMarkerGroup" value="1" />
  <property name="POIMarkerTags" value="" />
  <property name="POIMarkerType" value="PartSpawn" />
  <property name="POIMarkerPartToSpawn" value="part_driveway_countryresidential_03" />
  <property name="POIMarkerPartRotations" value="1" />
  <property name="POIMarkerPartSpawnChance" value="1" />
  <property name="Zoning" value="none" />
  <property class="IndexedBlockOffsets">
    <property class="quest_wood_trees">
      <property name="0" value="34, 1, 8" />
      <property name="1" value="31, 1, 14" />
    </property>
    <property class="POILight">
      <property name="0" value="31, 4, 37" />
      <property name="1" value="22, 4, 39" />
    </property>
    <property class="challenge_cars">
      <property name="0" value="34, 1, 20" />
    </property>
    <property class="challenge_mech_parts">
      <property name="0" value="24, 1, 6" />
      <property name="1" value="27, 1, 6" />
    </property>
    <property class="TraderOnOff">
      <property name="0" value="26, 12, 37" />
    </property>
    <property class="challenge_sinks">
      <property name="0" value="27, 2, 23" />
      <property name="1" value="27, 3, 23" />
      <property name="2" value="21, 2, 32" />
      <property name="3" value="21, 3, 32" />
      <property name="4" value="27, 2, 32" />
      <property name="5" value="21, 3, 36" />
      <property name="6" value="24, 3, 36" />
      <property name="7" value="27, 2, 36" />
      <property name="8" value="27, 3, 36" />
    </property>
    <property class="challenge_polymers">
      <property name="0" value="27, 8, 24" />
      <property name="1" value="29, 7, 31" />
    </property>
    <property class="FetchContainer">
      <property name="0" value="26, 10, 24" />
    </property>
    <property class="challenge_gore">
      <property name="0" value="32, 1, 4" />
    </property>
    <property class="Rally">
      <property name="0" value="40, 1, 21" />
    </property>
  </property>
  <property class="Stats">
    <property name="TotalVertices" value="449483" />
    <property name="TotalTriangles" value="232807" />
    <property class="BlockEntities">
      <property name="Vertices" value="386800" />
      <property name="Triangles" value="192841" />
    </property>
    <property class="ChunkMeshes0">
      <property name="Vertices" value="55653" />
      <property name="Triangles" value="31418" />
    </property>
    <property class="ChunkMeshes1">
      <property name="Vertices" value="0" />
      <property name="Triangles" value="0" />
    </property>
    <property class="ChunkMeshes2">
      <property name="Vertices" value="0" />
      <property name="Triangles" value="0" />
    </property>
    <property class="ChunkMeshes3">
      <property name="Vertices" value="2320" />
      <property name="Triangles" value="1160" />
    </property>
    <property class="ChunkMeshes4">
      <property name="Vertices" value="0" />
      <property name="Triangles" value="0" />
    </property>
    <property class="ChunkMeshes5">
      <property name="Vertices" value="4710" />
      <property name="Triangles" value="7388" />
    </property>
  </property>
</prefab>