<?xml version="1.0" encoding="UTF-8"?>
<prefab>
  <property name="CopyAirBlocks" value="True" />
  <property name="AllowTopSoilDecorations" value="True" />
  <property name="TraderArea" value="False" />
  <property name="ExcludeDistantPOIMesh" value="False" />
  <property name="ExcludePOICulling" value="False" />
  <property name="QuestTags" value="clear, fetch, infested" />
  <property name="DifficultyTier" value="2" />
  <property name="RotationToFaceNorth" value="1" />
  <property name="YOffset" value="-11" />
  <property name="DistantPOIYOffset" value="0" />
  <property name="EditorGroups" value="destroyed, tier_2, pre_a20" />
  <property name="SleeperVolumeStart" value="29, 11, 21#32, 2, 36#29, 11, 0#31, 12, 5#50, 2, 16" />
  <property name="SleeperVolumeSize" value="30, 2, 38#20, 8, 22#29, 1, 21#18, 6, 15#9, 9, 11" />
  <property name="SleeperVolumeGroup" value="GroupGenericZombie,5,7,GroupGenericZombie,4,4,GroupGenericZombie,1,2,GroupGenericZombie,5,6,GroupZomSoldier,2,3" />
  <property name="SleeperVolumeGameStageAdjust" value=",,,," />
  <property name="SleeperIsLootVolume" value="False,False,False,False,False" />
  <property name="SleeperIsQuestExclude" value="False,False,False,False,False" />
  <property name="SleeperVolumeFlags" value="0,0,0,0,0" />
  <property name="SleeperVolumeGroupId" value="0,0,0,0,0" />
  <property name="ShowQuestClearCount" value="1" />
  <property name="POIMarkerSize" value="3, 13, 9#27, 2, 18#27, 2, 18#27, 2, 18#27, 2, 18#27, 2, 18#27, 2, 18" />
  <property name="POIMarkerStart" value="60, 10, 12#1, 10, 1#1, 10, 21#1, 10, 41#1, 10, 41#1, 10, 21#1, 10, 1" />
  <property name="POIMarkerGroup" value="1,Field3,Field2,Field1,Field1,Field2,Field3" />
  <property name="POIMarkerTags" value="######" />
  <property name="POIMarkerType" value="PartSpawn,PartSpawn,PartSpawn,PartSpawn,PartSpawn,PartSpawn,PartSpawn" />
  <property name="POIMarkerPartToSpawn" value="part_driveway_rural_10,part_xcpv_grass_27x18,part_xcpv_grass_27x18,part_xcpv_grass_27x18,part_xcpv_goldenrod_27x18,part_xcpv_goldenrod_27x18,part_xcpv_goldenrod_27x18" />
  <property name="POIMarkerPartRotations" value="1,1,1,1,1,1,1" />
  <property name="POIMarkerPartSpawnChance" value="1,1,0.6,1,0.4,1,0.4" />
  <property name="Tags" value="rural" />
  <property name="DuplicateRepeatDistance" value="16000" />
  <property name="PrefabSize" value="60, 31, 60" />
  <property name="SleeperVolumeTriggeredBy" value=" # # # # " />
  <property name="ThemeTags" value="cptwin7" />
  <property name="ThemeRepeatDistance" value="2000" />
  <property name="Zoning" value="none" />
  <property class="IndexedBlockOffsets">
    <property class="quest_wood_trees">
      <property name="0" value="57, 11, 51" />
      <property name="1" value="53, 11, 55" />
      <property name="2" value="48, 11, 57" />
    </property>
    <property class="POILight">
      <property name="0" value="51, 12, 53" />
      <property name="1" value="48, 4, 54" />
    </property>
    <property class="challenge_leather">
      <property name="0" value="39, 12, 7" />
      <property name="1" value="35, 16, 8" />
      <property name="2" value="36, 16, 8" />
      <property name="3" value="39, 12, 8" />
      <property name="4" value="35, 12, 9" />
      <property name="5" value="36, 12, 9" />
      <property name="6" value="36, 16, 9" />
      <property name="7" value="37, 12, 9" />
      <property name="8" value="38, 12, 9" />
      <property name="9" value="39, 12, 9" />
      <property name="10" value="33, 16, 10" />
      <property name="11" value="33, 16, 11" />
      <property name="12" value="34, 16, 11" />
    </property>
    <property class="FetchContainer">
      <property name="0" value="57, 2, 22" />
    </property>
    <property class="challenge_polymers">
      <property name="0" value="52, 11, 7" />
      <property name="1" value="56, 12, 7" />
      <property name="2" value="52, 11, 10" />
      <property name="3" value="56, 12, 10" />
    </property>
    <property class="TraderOnOff">
      <property name="0" value="54, 11, 12" />
    </property>
    <property class="challenge_sinks">
      <property name="0" value="48, 2, 56" />
    </property>
    <property class="challenge_mech_parts">
      <property name="0" value="46, 13, 33" />
      <property name="1" value="55, 12, 38" />
    </property>
    <property class="challenge_pallet">
      <property name="0" value="50, 11, 39" />
    </property>
    <property class="Rally">
      <property name="0" value="59, 11, 20" />
    </property>
    <property class="challenge_cars">
      <property name="0" value="46, 11, 28" />
    </property>
  </property>
  <property class="Stats">
    <property name="TotalVertices" value="936442" />
    <property name="TotalTriangles" value="533350" />
    <property class="BlockEntities">
      <property name="Vertices" value="821718" />
      <property name="Triangles" value="447549" />
    </property>
    <property class="ChunkMeshes0">
      <property name="Vertices" value="77314" />
      <property name="Triangles" value="49653" />
    </property>
    <property class="ChunkMeshes1">
      <property name="Vertices" value="10880" />
      <property name="Triangles" value="5440" />
    </property>
    <property class="ChunkMeshes2">
      <property name="Vertices" value="2044" />
      <property name="Triangles" value="1392" />
    </property>
    <property class="ChunkMeshes3">
      <property name="Vertices" value="10464" />
      <property name="Triangles" value="5232" />
    </property>
    <property class="ChunkMeshes4">
      <property name="Vertices" value="0" />
      <property name="Triangles" value="0" />
    </property>
    <property class="ChunkMeshes5">
      <property name="Vertices" value="14022" />
      <property name="Triangles" value="24084" />
    </property>
  </property>
</prefab>