<?xml version="1.0" encoding="UTF-8"?>
<prefab>
  <property name="CopyAirBlocks" value="True" />
  <property name="AllowTopSoilDecorations" value="True" />
  <property name="YOffset" value="-11" />
  <property name="RotationToFaceNorth" value="2" />
  <property name="ExcludeDistantPOIMesh" value="True" />
  <property name="TraderArea" value="False" />
  <property name="SleeperVolumeSize" value="22, 7, 6#15, 8, 12#9, 7, 8#11, 6, 12#5, 6, 9#5, 6, 9#12, 10, 22#13, 10, 16#12, 9, 19#9, 8, 7#16, 10, 5" />
  <property name="SleeperVolumeStart" value="45, 0, 11#48, 0, 30#51, 0, 42#51, 0, 50#46, 0, 46#41, 0, 50#34, 0, 59#58, 0, 70#46, 0, 67#62, 0, 63#30, 0, 81" />
  <property name="SleeperVolumeGroup" value="zombieSpiderFeral,6,6,zombieSpiderFeral,4,4,zombieSpiderFeral,2,2,zombieSpiderFeral,6,6,zombieSpiderFeral,2,2,zombieSpiderFeral,2,2,zombieSpiderFeral,4,4,zombieSpiderFeral,1,1,zombieSpiderFeral,3,3,zombieSpiderFeral,7,7,zombieSpiderFeral,2,2" />
  <property name="SleeperIsLootVolume" value="False,False,False,False,False,False,False,False,False,False,False" />
  <property name="DistantPOIYOffset" value="0" />
  <property name="EditorGroups" value="cave, tier_3, pre_a20" />
  <property name="SleeperIsBossVolume" value="False" />
  <property name="DifficultyTier" value="3" />
  <property name="ExcludePOICulling" value="False" />
  <property name="SleeperVolumeGroupId" value="0,0,0,0,0,0,0,0,0,0,0" />
  <property name="SleeperVolumeFlags" value="3,2,2,2,2,2,2,2,2,2,2" />
  <property name="ShowQuestClearCount" value="2" />
  <property name="SleeperIsQuestExclude" value="False,False,False,False,False,False,False,False,False,False,False" />
  <property name="PrefabSize" value="100, 31, 100" />
  <property name="Tags" value="wilderness" />
  <property name="SleeperVolumeTriggeredBy" value="1# # # # # # # # # # " />
  <property name="TriggerVolumeSize" value="10, 5, 8" />
  <property name="TriggerVolumeStart" value="51, 0, 21" />
  <property name="TriggerVolumeTriggers" value="1" />
  <property name="QuestTags" value="clear, fetch, infested" />
  <property name="ThemeTags" value="cpvwild" />
  <property name="ThemeRepeatDistance" value="0" />
  <property name="DuplicateRepeatDistance" value="16000" />
  <property name="Zoning" value="none" />
  <property class="Stats">
    <property name="TotalVertices" value="376776" />
    <property name="TotalTriangles" value="268635" />
    <property class="BlockEntities">
      <property name="Vertices" value="336992" />
      <property name="Triangles" value="206251" />
    </property>
    <property class="ChunkMeshes0">
      <property name="Vertices" value="1944" />
      <property name="Triangles" value="1336" />
    </property>
    <property class="ChunkMeshes1">
      <property name="Vertices" value="0" />
      <property name="Triangles" value="0" />
    </property>
    <property class="ChunkMeshes2">
      <property name="Vertices" value="0" />
      <property name="Triangles" value="0" />
    </property>
    <property class="ChunkMeshes3">
      <property name="Vertices" value="0" />
      <property name="Triangles" value="0" />
    </property>
    <property class="ChunkMeshes4">
      <property name="Vertices" value="0" />
      <property name="Triangles" value="0" />
    </property>
    <property class="ChunkMeshes5">
      <property name="Vertices" value="37840" />
      <property name="Triangles" value="61048" />
    </property>
  </property>
  <property class="IndexedBlockOffsets">
    <property class="Rally">
      <property name="0" value="47, 11, 12" />
    </property>
    <property class="quest_wood_trees">
      <property name="0" value="66, 11, 26" />
    </property>
    <property class="quest_stone_boulder">
      <property name="0" value="66, 11, 42" />
    </property>
    <property class="challenge_gore">
      <property name="0" value="70, 3, 83" />
    </property>
    <property class="FetchContainer">
      <property name="0" value="64, 3, 84" />
    </property>
    <property class="challenge_cars">
      <property name="0" value="41, 6, 77" />
    </property>
    <property class="challenge_steel">
      <property name="0" value="42, 5, 80" />
    </property>
    <property class="challenge_polymers">
      <property name="0" value="62, 4, 77" />
    </property>
    <property class="challenge_leather">
      <property name="0" value="66, 4, 79" />
    </property>
    <property class="POILight">
      <property name="0" value="69, 3, 70" />
    </property>
  </property>
</prefab>