<?xml version="1.0" encoding="UTF-8"?>
<prefab>
  <property name="CopyAirBlocks" value="True" />
  <property name="ExcludeDistantPOIMesh" value="False" />
  <property name="ExcludePOICulling" value="False" />
  <property name="DistantPOIYOffset" value="0" />
  <property name="AllowTopSoilDecorations" value="True" />
  <property name="DifficultyTier" value="2" />
  <property name="ShowQuestClearCount" value="1" />
  <property name="TraderArea" value="False" />
  <property name="PrefabSize" value="42, 17, 42" />
  <property name="RotationToFaceNorth" value="2" />
  <property name="SleeperVolumeSize" value="12, 4, 17#12, 7, 7#4, 1, 14#16, 3, 10#16, 2, 11#22, 3, 25#7, 2, 18" />
  <property name="SleeperVolumeStart" value="20, 2, 21#11, 3, 14#20, 9, 14#17, 8, 14#17, 9, 28#11, 13, 14#32, 2, 21" />
  <property name="SleeperVolumeGroupId" value="0,0,0,0,0,0,0" />
  <property name="SleeperVolumeGroup" value="GroupGhostTown,7,7,GroupGhostTown,4,4,GroupGhostTown,1,1,GroupGhostTown,3,4,GroupGhostTown,4,4,GroupGhostTown,4,4,GroupGhostTown,3,3" />
  <property name="SleeperIsLootVolume" value="False,True,True,False,False,False,False" />
  <property name="SleeperIsQuestExclude" value="False,False,False,False,False,False,False" />
  <property name="SleeperVolumeFlags" value="2,0,2,0,0,0,3" />
  <property name="SleeperVolumeTriggeredBy" value=" # # # # # #3" />
  <property name="YOffset" value="-2" />
  <property name="EditorGroups" value="oldwest, tier_2, bar, entertainment" />
  <property name="Tags" value="oldwest" />
  <property name="DuplicateRepeatDistance" value="16000" />
  <property name="QuestTags" value="clear, fetch, restore_power, infested" />
  <property name="Zoning" value="none" />
  <property name="TriggerVolumeSize" value="12, 3, 1" />
  <property name="TriggerVolumeStart" value="20, 9, 30" />
  <property name="TriggerVolumeTriggers" value="3" />
  <property class="IndexedBlockOffsets">
    <property class="Rally">
      <property name="0" value="1, 2, 1" />
    </property>
    <property class="POILight">
      <property name="0" value="38, 4, 19" />
    </property>
    <property class="TraderOnOff">
      <property name="0" value="25, 10, 30" />
    </property>
    <property class="quest_feather">
      <property name="0" value="32, 15, 26" />
      <property name="1" value="24, 15, 30" />
    </property>
    <property class="FetchContainer">
      <property name="0" value="21, 4, 37" />
    </property>
    <property class="challenge_cars">
      <property name="0" value="7, 2, 25" />
    </property>
    <property class="challenge_polymers">
      <property name="0" value="29, 9, 37" />
    </property>
    <property class="challenge_sinks">
      <property name="0" value="21, 14, 37" />
      <property name="1" value="22, 14, 37" />
      <property name="2" value="23, 7, 37" />
      <property name="3" value="23, 14, 37" />
      <property name="4" value="24, 14, 37" />
      <property name="5" value="26, 7, 37" />
      <property name="6" value="26, 10, 37" />
      <property name="7" value="27, 10, 37" />
      <property name="8" value="30, 7, 37" />
    </property>
    <property class="challenge_mech_parts">
      <property name="0" value="24, 3, 28" />
      <property name="1" value="31, 3, 28" />
      <property name="2" value="28, 14, 35" />
    </property>
    <property class="challenge_gore">
      <property name="0" value="24, 10, 37" />
    </property>
    <property class="QuestRestorePower">
      <property name="0" value="25, 3, 28" />
      <property name="1" value="24, 14, 36" />
    </property>
  </property>
  <property class="Stats">
    <property name="TotalVertices" value="523768" />
    <property name="TotalTriangles" value="197361" />
    <property class="BlockEntities">
      <property name="Vertices" value="448318" />
      <property name="Triangles" value="147852" />
    </property>
    <property class="ChunkMeshes0">
      <property name="Vertices" value="69856" />
      <property name="Triangles" value="41277" />
    </property>
    <property class="ChunkMeshes1">
      <property name="Vertices" value="0" />
      <property name="Triangles" value="0" />
    </property>
    <property class="ChunkMeshes2">
      <property name="Vertices" value="616" />
      <property name="Triangles" value="388" />
    </property>
    <property class="ChunkMeshes3">
      <property name="Vertices" value="0" />
      <property name="Triangles" value="0" />
    </property>
    <property class="ChunkMeshes4">
      <property name="Vertices" value="0" />
      <property name="Triangles" value="0" />
    </property>
    <property class="ChunkMeshes5">
      <property name="Vertices" value="4978" />
      <property name="Triangles" value="7844" />
    </property>
  </property>
</prefab>