<?xml version="1.0" encoding="UTF-8"?>
<prefab>
  <property name="CopyAirBlocks" value="True" />
  <property name="ExcludeDistantPOIMesh" value="False" />
  <property name="ExcludePOICulling" value="False" />
  <property name="DistantPOIYOffset" value="0" />
  <property name="AllowTopSoilDecorations" value="True" />
  <property name="DifficultyTier" value="3" />
  <property name="ShowQuestClearCount" value="2" />
  <property name="TraderArea" value="False" />
  <property name="PrefabSize" value="42, 16, 42" />
  <property name="RotationToFaceNorth" value="3" />
  <property name="YOffset" value="-3" />
  <property name="SleeperVolumeSize" value="5, 2, 7#11, 3, 11#9, 3, 15#2, 1, 3#16, 2, 23#2, 1, 3#15, 3, 11#8, 3, 11#8, 3, 3#2, 1, 2#4, 2, 6#11, 3, 9" />
  <property name="SleeperVolumeStart" value="28, 3, 19#13, 3, 26#24, 3, 22#30, 3, 6#18, 3, 3#26, 8, 21#24, 8, 26#13, 8, 26#19, 8, 13#25, 8, 5#28, 8, 11#19, 8, 4" />
  <property name="SleeperVolumeGroupId" value="0,0,0,0,0,0,0,0,0,0,0,0" />
  <property name="SleeperVolumeGroup" value="GroupGenericZombie,1,1,GroupGenericZombie,6,6,GroupGenericZombie,3,3,GroupZomBadass,2,2,GroupGenericZombie,5,5,GroupZomBadass,3,3,GroupGenericZombie,4,4,GroupGenericZombie,3,6,GroupGenericZombie,1,1,GroupZomBadass,2,2,GroupZomBadass,2,2,GroupGenericZombie,3,3" />
  <property name="SleeperIsLootVolume" value="True,True,False,True,False,False,False,False,False,True,False,False" />
  <property name="SleeperIsQuestExclude" value="False,False,False,False,False,False,False,False,False,False,False,False" />
  <property name="SleeperVolumeFlags" value="0,3,0,3,3,3,0,3,2,3,3,0" />
  <property name="SleeperVolumeTriggeredBy" value=" #1# #2#2#3# #4# #5#5# " />
  <property name="TriggerVolumeSize" value="2, 2, 2" />
  <property name="TriggerVolumeStart" value="31, 5, 17" />
  <property name="TriggerVolumeTriggers" value="3" />
  <property name="EditorGroups" value="tier_3, post_a20" />
  <property name="QuestTags" value="clear, fetch, infested" />
  <property name="Tags" value="countryresidential" />
  <property name="DuplicateRepeatDistance" value="16000" />
  <property name="POIMarkerSize" value="1, 13, 11" />
  <property name="POIMarkerStart" value="-1, 2, 26" />
  <property name="POIMarkerGroup" value="1" />
  <property name="POIMarkerTags" value="" />
  <property name="POIMarkerType" value="PartSpawn" />
  <property name="POIMarkerPartToSpawn" value="part_driveway_countryresidential_04" />
  <property name="POIMarkerPartRotations" value="3" />
  <property name="POIMarkerPartSpawnChance" value="1" />
  <property name="Zoning" value="none" />
  <property class="IndexedBlockOffsets">
    <property class="quest_wood">
      <property name="0" value="15, 3, 38" />
      <property name="1" value="6, 3, 39" />
      <property name="2" value="7, 3, 40" />
      <property name="3" value="7, 3, 41" />
    </property>
    <property class="Rally">
      <property name="0" value="0, 3, 37" />
    </property>
    <property class="challenge_leather">
      <property name="0" value="22, 3, 22" />
      <property name="1" value="24, 3, 25" />
      <property name="2" value="27, 3, 30" />
      <property name="3" value="28, 3, 30" />
      <property name="4" value="29, 3, 30" />
      <property name="5" value="30, 3, 30" />
      <property name="6" value="31, 3, 30" />
      <property name="7" value="27, 3, 31" />
      <property name="8" value="31, 3, 31" />
      <property name="9" value="27, 3, 32" />
      <property name="10" value="29, 3, 32" />
      <property name="11" value="31, 3, 32" />
      <property name="12" value="27, 3, 33" />
      <property name="13" value="31, 3, 33" />
      <property name="14" value="27, 3, 34" />
    </property>
    <property class="POILight">
      <property name="0" value="22, 6, 21" />
      <property name="1" value="25, 6, 21" />
      <property name="2" value="28, 6, 21" />
      <property name="3" value="30, 5, 22" />
      <property name="4" value="31, 6, 22" />
      <property name="5" value="22, 6, 23" />
      <property name="6" value="25, 6, 23" />
      <property name="7" value="28, 6, 23" />
      <property name="8" value="30, 5, 23" />
      <property name="9" value="30, 5, 24" />
      <property name="10" value="22, 6, 25" />
      <property name="11" value="25, 6, 25" />
      <property name="12" value="28, 6, 25" />
      <property name="13" value="31, 6, 25" />
      <property name="14" value="24, 10, 27" />
      <property name="15" value="25, 6, 27" />
      <property name="16" value="27, 10, 27" />
      <property name="17" value="28, 6, 27" />
      <property name="18" value="30, 10, 27" />
      <property name="19" value="31, 6, 27" />
      <property name="20" value="21, 6, 28" />
      <property name="21" value="21, 10, 28" />
      <property name="22" value="21, 10, 29" />
      <property name="23" value="23, 10, 29" />
      <property name="24" value="25, 6, 29" />
      <property name="25" value="25, 11, 29" />
      <property name="26" value="27, 11, 29" />
      <property name="27" value="28, 6, 29" />
      <property name="28" value="29, 10, 29" />
      <property name="29" value="31, 6, 29" />
      <property name="30" value="32, 10, 29" />
      <property name="31" value="22, 10, 30" />
      <property name="32" value="29, 10, 30" />
      <property name="33" value="21, 6, 31" />
      <property name="34" value="25, 6, 31" />
      <property name="35" value="25, 11, 31" />
      <property name="36" value="27, 11, 31" />
      <property name="37" value="28, 6, 31" />
      <property name="38" value="29, 8, 31" />
      <property name="39" value="30, 10, 31" />
      <property name="40" value="31, 6, 31" />
      <property name="41" value="34, 13, 31" />
      <property name="42" value="21, 8, 32" />
      <property name="43" value="23, 11, 32" />
      <property name="44" value="27, 8, 32" />
      <property name="45" value="29, 10, 32" />
      <property name="46" value="21, 11, 33" />
      <property name="47" value="23, 11, 33" />
      <property name="48" value="25, 6, 33" />
      <property name="49" value="26, 10, 33" />
      <property name="50" value="27, 11, 33" />
      <property name="51" value="28, 6, 33" />
      <property name="52" value="31, 6, 33" />
      <property name="53" value="21, 6, 34" />
      <property name="54" value="29, 10, 34" />
      <property name="55" value="32, 10, 34" />
      <property name="56" value="21, 8, 35" />
      <property name="57" value="25, 6, 35" />
      <property name="58" value="27, 8, 35" />
      <property name="59" value="28, 6, 35" />
      <property name="60" value="31, 6, 35" />
      <property name="61" value="27, 3, 36" />
      <property name="62" value="31, 3, 36" />
    </property>
    <property class="challenge_sinks">
      <property name="0" value="30, 3, 24" />
      <property name="1" value="30, 4, 24" />
      <property name="2" value="23, 3, 27" />
      <property name="3" value="23, 3, 28" />
      <property name="4" value="23, 3, 29" />
      <property name="5" value="21, 8, 33" />
      <property name="6" value="27, 8, 33" />
    </property>
    <property class="TraderOnOff">
      <property name="0" value="29, 3, 22" />
      <property name="1" value="22, 3, 26" />
      <property name="2" value="27, 8, 28" />
      <property name="3" value="30, 8, 28" />
    </property>
    <property class="challenge_mech_parts">
      <property name="0" value="26, 8, 29" />
      <property name="1" value="30, 8, 35" />
    </property>
    <property class="FetchContainer">
      <property name="0" value="30, 8, 34" />
      <property name="1" value="23, 8, 36" />
    </property>
    <property class="challenge_polymers">
      <property name="0" value="22, 8, 25" />
      <property name="1" value="23, 4, 28" />
    </property>
  </property>
  <property class="Stats">
    <property name="TotalVertices" value="451009" />
    <property name="TotalTriangles" value="178329" />
    <property class="BlockEntities">
      <property name="Vertices" value="359551" />
      <property name="Triangles" value="123980" />
    </property>
    <property class="ChunkMeshes0">
      <property name="Vertices" value="75048" />
      <property name="Triangles" value="40373" />
    </property>
    <property class="ChunkMeshes1">
      <property name="Vertices" value="0" />
      <property name="Triangles" value="0" />
    </property>
    <property class="ChunkMeshes2">
      <property name="Vertices" value="904" />
      <property name="Triangles" value="452" />
    </property>
    <property class="ChunkMeshes3">
      <property name="Vertices" value="10192" />
      <property name="Triangles" value="5096" />
    </property>
    <property class="ChunkMeshes4">
      <property name="Vertices" value="16" />
      <property name="Triangles" value="8" />
    </property>
    <property class="ChunkMeshes5">
      <property name="Vertices" value="5298" />
      <property name="Triangles" value="8420" />
    </property>
  </property>
</prefab>