<?xml version="1.0" encoding="UTF-8"?>
<prefab>
  <property name="CopyAirBlocks" value="True" />
  <property name="AllowTopSoilDecorations" value="True" />
  <property name="TraderArea" value="False" />
  <property name="ExcludeDistantPOIMesh" value="False" />
  <property name="ExcludePOICulling" value="False" />
  <property name="DifficultyTier" value="1" />
  <property name="RotationToFaceNorth" value="2" />
  <property name="YOffset" value="-1" />
  <property name="DistantPOIYOffset" value="0" />
  <property name="EditorGroups" value="tier_1, pre_a20" />
  <property name="SleeperVolumeStart" value="2, 1, 3" />
  <property name="SleeperVolumeSize" value="56, 5, 53" />
  <property name="SleeperVolumeGroup" value="GroupGenericZombie,10,10" />
  <property name="SleeperVolumeGameStageAdjust" value="easy" />
  <property name="SleeperIsLootVolume" value="False" />
  <property name="SleeperIsQuestExclude" value="False" />
  <property name="SleeperVolumeFlags" value="0" />
  <property name="SleeperVolumeGroupId" value="0" />
  <property name="ShowQuestClearCount" value="1" />
  <property name="Tags" value="rural" />
  <property name="DuplicateRepeatDistance" value="16000" />
  <property name="QuestTags" value="clear, fetch, infested" />
  <property name="POIMarkerSize" value="7, 13, 3#6, 13, 3#8, 5, 11" />
  <property name="POIMarkerStart" value="1, 0, -3#53, 0, -3#23, 1, 21" />
  <property name="POIMarkerGroup" value="1,2,3" />
  <property name="POIMarkerTags" value="##" />
  <property name="POIMarkerType" value="PartSpawn,PartSpawn,PartSpawn" />
  <property name="POIMarkerPartToSpawn" value="part_driveway_rural_08,part_driveway_rural_01,part_harverster" />
  <property name="POIMarkerPartRotations" value="2,2,0" />
  <property name="POIMarkerPartSpawnChance" value="1,1,1" />
  <property name="PrefabSize" value="60, 20, 60" />
  <property name="SleeperVolumeTriggeredBy" value=" " />
  <property name="Zoning" value="none" />
  <property class="IndexedBlockOffsets">
    <property class="Rally">
      <property name="0" value="7, 1, 0" />
    </property>
    <property class="challenge_gore">
      <property name="0" value="32, 1, 31" />
    </property>
    <property class="challenge_mech_parts">
      <property name="0" value="39, 1, 7" />
      <property name="1" value="41, 1, 7" />
      <property name="2" value="39, 1, 12" />
      <property name="3" value="41, 1, 12" />
    </property>
    <property class="challenge_polymers">
      <property name="0" value="39, 1, 8" />
      <property name="1" value="41, 1, 8" />
      <property name="2" value="43, 1, 8" />
      <property name="3" value="39, 1, 11" />
      <property name="4" value="41, 1, 11" />
      <property name="5" value="43, 1, 11" />
    </property>
    <property class="challenge_sinks">
      <property name="0" value="40, 2, 9" />
      <property name="1" value="41, 2, 9" />
      <property name="2" value="40, 2, 10" />
      <property name="3" value="41, 2, 10" />
    </property>
    <property class="POILight">
      <property name="0" value="44, 1, 9" />
      <property name="1" value="44, 1, 10" />
    </property>
    <property class="FetchContainer">
      <property name="0" value="40, 1, 49" />
    </property>
    <property class="quest_wood_trees">
      <property name="0" value="50, 1, 49" />
    </property>
  </property>
  <property class="Stats">
    <property name="TotalVertices" value="207126" />
    <property name="TotalTriangles" value="98054" />
    <property class="BlockEntities">
      <property name="Vertices" value="182662" />
      <property name="Triangles" value="72708" />
    </property>
    <property class="ChunkMeshes0">
      <property name="Vertices" value="11298" />
      <property name="Triangles" value="7258" />
    </property>
    <property class="ChunkMeshes1">
      <property name="Vertices" value="0" />
      <property name="Triangles" value="0" />
    </property>
    <property class="ChunkMeshes2">
      <property name="Vertices" value="0" />
      <property name="Triangles" value="0" />
    </property>
    <property class="ChunkMeshes3">
      <property name="Vertices" value="3432" />
      <property name="Triangles" value="1716" />
    </property>
    <property class="ChunkMeshes4">
      <property name="Vertices" value="0" />
      <property name="Triangles" value="0" />
    </property>
    <property class="ChunkMeshes5">
      <property name="Vertices" value="9734" />
      <property name="Triangles" value="16372" />
    </property>
  </property>
</prefab>