<configs>

	
<!--
	<append xpath="windows">
	
	
		<window name="BozwardoSkillIndicator" width="1000" height="100" anchor="CenterBottom" pos="0,0" controller="ToolbeltWindow" cursor_area="false">
			<rect pos="-390,-170" >
					

				<rect pos="0,0">

						<sprite depth="5" name="windowicon" style="icon32px" pos="308,0" pivot="center" justify="center" width="80" height="80" sprite="SkillDisplay" color="{itemicontint}" visible="{cvar(SkillSlots_Temp:true;false;false)}" atlas="ItemIconAtlas"/>
						

					


						<sprite depth="4" name="itemPreview" pos="308,0" width="73" height="73" atlas="ItemIconAtlas" sprite="VineSnap" color="0,255,0" pivot="center" visible="{cvar(VineSnapFirstSkill_Temp:true;false;false)}" foregroundlayer="true"/>
						<sprite depth="4" name="itemPreview" pos="308,0" width="73" height="73" atlas="ItemIconAtlas" sprite="PoisonTouch" color="0,255,0" pivot="center" visible="{cvar(PoisonTouchFirstSkill_Temp:true;false;false)}" foregroundlayer="true"/>
						<sprite depth="4" name="itemPreview" pos="308,0" width="73" height="73" atlas="ItemIconAtlas" sprite="CallOfTheWolves" color="{cvar(COTWCooldownRed)},{cvar(COTWCooldownGreen)},{cvar(COTWCooldownBlue)}" pivot="center" visible="{cvar(CallOfTheWolvesFirstSkill_Temp:true;false;false)}" foregroundlayer="true"/>
						<sprite depth="4" name="itemPreview" pos="308,0" width="73" height="73" atlas="ItemIconAtlas" sprite="RageOfTheForest" color="0,255,0" pivot="center" visible="{cvar(RageOfTheForestFirstSkill_Temp:true;false;false)}" foregroundlayer="true"/>
						<sprite depth="4" name="itemPreview" pos="308,0" width="73" height="73" atlas="ItemIconAtlas" sprite="RampidSprouts" color="0,255,0" pivot="center" visible="{cvar(RampidSproutsFirstSkill_Temp:true;false;false)}" foregroundlayer="true"/>
						<sprite depth="4" name="itemPreview" pos="308,0" width="73" height="73" atlas="ItemIconAtlas" sprite="BuffAllies" color="0,255,0" pivot="center" visible="{cvar(BuffAlliesFirstSkill_Temp:true;false;false)}" foregroundlayer="true"/>
						<sprite depth="4" name="itemPreview" pos="308,0" width="73" height="73" atlas="ItemIconAtlas" sprite="HealingMist" color="0,255,0" pivot="center" visible="{cvar(HealingMistFirstSkill_Temp:true;false;false)}" foregroundlayer="true"/>
						<sprite depth="4" name="itemPreview" pos="308,0" width="73" height="73" atlas="ItemIconAtlas" sprite="AcidRain" color="0,255,0" pivot="center" visible="{cvar(AcidRainFirstSkill_Temp:true;false;false)}" foregroundlayer="true"/>
						<sprite depth="4" name="itemPreview" pos="308,0" width="73" height="73" atlas="ItemIconAtlas" sprite="HardSkin" color="0,255,0" pivot="center" visible="{cvar(HardSkinFirstSkill_Temp:true;false;false)}" foregroundlayer="true"/>
						

					
						<sprite depth="4" name="itemPreview" pos="308,0" width="73" height="73" atlas="ItemIconAtlas" sprite="ExplodingVultures" color="0,255,0" pivot="center" visible="{cvar(ExplodingVulturesFirstSkill_Temp:true;false;false)}" foregroundlayer="true"/>
						<sprite depth="4" name="itemPreview" pos="308,0" width="73" height="73" atlas="ItemIconAtlas" sprite="GustingWind" color="0,255,0" pivot="center" visible="{cvar(GustingwindFirstSkill_Temp:true;false;false)}" foregroundlayer="true"/>
						<sprite depth="4" name="itemPreview" pos="308,0" width="73" height="73" atlas="ItemIconAtlas" sprite="Spawningvultures" color="0,255,0" pivot="center" visible="{cvar(SpawningvulturesFirstSkill_Temp:true;false;false)}" foregroundlayer="true"/>
						<sprite depth="4" name="itemPreview" pos="308,0" width="73" height="73" atlas="ItemIconAtlas" sprite="Quicksand" color="0,255,0" pivot="center" visible="{cvar(QuickSandFirstSkill_Temp:true;false;false)}" foregroundlayer="true"/>
						<sprite depth="4" name="itemPreview" pos="308,0" width="73" height="73" atlas="ItemIconAtlas" sprite="Entoumb" color="0,255,0" pivot="center" visible="{cvar(EntoumbFirstSkill_Temp:true;false;false)}" foregroundlayer="true"/>
						<sprite depth="4" name="itemPreview" pos="308,0" width="73" height="73" atlas="ItemIconAtlas" sprite="TalonStrike" color="0,255,0" pivot="center" visible="{cvar(TalonStrikeFirstSkill_Temp:true;false;false)}" foregroundlayer="true"/>
						<sprite depth="4" name="itemPreview" pos="308,0" width="73" height="73" atlas="ItemIconAtlas" sprite="sandstorm" color="0,255,0" pivot="center" visible="{cvar(SandStormFirstSkill_Temp:true;false;false)}" foregroundlayer="true"/>
						<sprite depth="4" name="itemPreview" pos="308,0" width="73" height="73" atlas="ItemIconAtlas" sprite="Exhaustion" color="0,255,0" pivot="center" visible="{cvar(ExhaustionFirstSkill_Temp:true;false;false)}" foregroundlayer="true"/>
						<sprite depth="4" name="itemPreview" pos="308,0" width="73" height="73" atlas="ItemIconAtlas" sprite="SlowingTotem" color="0,255,0" pivot="center" visible="{cvar(SlowingTotemFirstSkill_Temp:true;false;false)}" foregroundlayer="true"/>
						

					
						<sprite depth="4" name="itemPreview" pos="308,0" width="73" height="73" atlas="ItemIconAtlas" sprite="BearCharge" color="0,255,200" pivot="center" visible="{cvar(BearChargeFirstSkill_Temp:true;false;false)}" foregroundlayer="true"/>
						<sprite depth="4" name="itemPreview" pos="308,0" width="73" height="73" atlas="ItemIconAtlas" sprite="Splice" color="0,255,200" pivot="center" visible="{cvar(SpliceFirstSkill_Temp:true;false;false)}" foregroundlayer="true"/>
						<sprite depth="4" name="itemPreview" pos="308,0" width="73" height="73" atlas="ItemIconAtlas" sprite="Avalanche" color="{cvar(AWR)},{cvar(AWG)},{cvar(AWB)}" pivot="center" visible="{cvar(ArcticWinterFirstSkill_Temp:true;false;false)}" foregroundlayer="true"/>
						<sprite depth="4" name="itemPreview" pos="308,0" width="73" height="73" atlas="ItemIconAtlas" sprite="GroundStomp" color="0,255,200" pivot="center" visible="{cvar(GroundSlamFirstSkill_Temp:true;false;false)}" foregroundlayer="true"/>
						<sprite depth="4" name="itemPreview" pos="308,0" width="73" height="73" atlas="ItemIconAtlas" sprite="GrizzlyBite" color="0,255,200" pivot="center" visible="{cvar(GrizzlyBiteFirstSkill_Temp:true;false;false)}" foregroundlayer="true"/>
						<sprite depth="4" name="itemPreview" pos="308,0" width="73" height="73" atlas="ItemIconAtlas" sprite="Maul" color="0,255,200" pivot="center" visible="{cvar(MaulFirstSkill_Temp:true;false;false)}" foregroundlayer="true"/>
						<sprite depth="4" name="itemPreview" pos="308,0" width="73" height="73" atlas="ItemIconAtlas" sprite="PhysicalResistance" color="0,255,200" pivot="center" visible="{cvar(PhysicalResistanceFirstSkill_Temp:true;false;false)}" foregroundlayer="true"/>
						<sprite depth="4" name="itemPreview" pos="308,0" width="73" height="73" atlas="ItemIconAtlas" sprite="FireResistance" color="0,255,200" pivot="center" visible="{cvar(FireResistanceFirstSkill_Temp:true;false;false)}" foregroundlayer="true"/>
						<sprite depth="4" name="itemPreview" pos="308,0" width="73" height="73" atlas="ItemIconAtlas" sprite="territorial" color="0,255,200" pivot="center" visible="{cvar(territorialFirstSkill_Temp:true;false;false)}" foregroundlayer="true"/>
						
						
								<sprite depth="5" height="66" width="66" name="background" pos="{cvar(CallOfTheWolvesCooldownPosition)},0" sprite="ui_game_filled_circle" color="150,150,150,255" justify="center" pivot="center" type="filled" fill="{cvar(CallOfTheWolvesCooldownTimerDisplayPercent)}" filldirection="radial360" visible="{cvar(CallOfTheWolvesFirstSkill_Temp:true;false;false)}"/>
							

							
								<sprite depth="5" height="66" width="66" name="background" pos="{cvar(BearChargeTimerPosition)},0" sprite="ui_game_filled_circle" color="200,50,50,300" justify="center" pivot="center" type="filled" fill="{cvar(BearChargeTimerDisplayPercent)}" filldirection="radial360" visible="{cvar(BearChargeCooldownVisible:true;false;false)}"/>
								<sprite depth="5" height="66" width="66" name="background" pos="{cvar(ArcticWinterTimerPosition)},0" sprite="ui_game_filled_circle" color="200,50,50,300" justify="center" pivot="center" type="filled" fill="{cvar(ArcticWinterTimerDisplayPercent)}" filldirection="radial360" visible="{cvar(ArcticWinterCooldownVisible:true;false;false)}"/>
								<label depth="6" name="TextContent" pos="{cvar(ArcticWinterTimerPosition)},-13" font_size="30" color="[white]" justify="center" pivot="center" text="x{cvar(ArcticWinterColdDisplay)}" height="30" visible="{cvar(ArcticWinterColdDisplayVisible:true;false;false)}"/>

								<sprite depth="5" height="66" width="66" name="background" pos="{cvar(GrizzlyBiteTimerPosition)},0" sprite="ui_game_filled_circle" color="200,50,50,300" justify="center" pivot="center" type="filled" fill="{cvar(GrizzlyBiteTimerDisplayPercent)}" filldirection="radial360" visible="{cvar(GrizzlyBiteCooldownVisible:true;false;false)}"/>
					
				</rect>		
				
				<rect pos="0,0">

					
					<sprite depth="5" name="itemPreview" pos="390,0" width="80" height="80" atlas="ItemIconAtlas" sprite="SkillDisplay" color="{itemicontint}" pivot="center" visible="{cvar(SkillSlots_Temp:true;false;false)}" foregroundlayer="true"/>
					
						<sprite depth="4" name="itemPreview" pos="390,0" width="73" height="73" atlas="ItemIconAtlas" sprite="VineSnap" color="0,255,0" pivot="center" visible="{cvar(VineSnapSecondSkill_Temp:true;false;false)}" foregroundlayer="true"/>
						<sprite depth="4" name="itemPreview" pos="390,0" width="73" height="73" atlas="ItemIconAtlas" sprite="PoisonTouch" color="0,255,0" pivot="center" visible="{cvar(PoisonTouchSecondSkill_Temp:true;false;false)}" foregroundlayer="true"/>
						<sprite depth="4" name="itemPreview" pos="390,0" width="73" height="73" atlas="ItemIconAtlas" sprite="CallOfTheWolves" color="{cvar(COTWCooldownRed)},{cvar(COTWCooldownGreen)},{cvar(COTWCooldownBlue)}" pivot="center" visible="{cvar(CallOfTheWolvesSecondSkill_Temp:true;false;false)}" foregroundlayer="true"/>
						<sprite depth="4" name="itemPreview" pos="390,0" width="73" height="73" atlas="ItemIconAtlas" sprite="RageOfTheForest" color="0,255,0" pivot="center" visible="{cvar(RageOfTheForestSecondSkill_Temp:true;false;false)}" foregroundlayer="true"/>
						<sprite depth="4" name="itemPreview" pos="390,0" width="73" height="73" atlas="ItemIconAtlas" sprite="RampidSprouts" color="0,255,0" pivot="center" visible="{cvar(RampidSproutsSecondSkill_Temp:true;false;false)}" foregroundlayer="true"/>
						<sprite depth="4" name="itemPreview" pos="390,0" width="73" height="73" atlas="ItemIconAtlas" sprite="BuffAllies" color="0,255,0" pivot="center" visible="{cvar(BuffAlliesSecondSkill_Temp:true;false;false)}" foregroundlayer="true"/>
						<sprite depth="4" name="itemPreview" pos="390,0" width="73" height="73" atlas="ItemIconAtlas" sprite="HealingMist" color="0,255,0" pivot="center" visible="{cvar(HealingMistSecondSkill_Temp:true;false;false)}" foregroundlayer="true"/>
						<sprite depth="4" name="itemPreview" pos="390,0" width="73" height="73" atlas="ItemIconAtlas" sprite="AcidRain" color="0,255,0" pivot="center" visible="{cvar(AcidRainSecondSkill_Temp:true;false;false)}" foregroundlayer="true"/>
						<sprite depth="4" name="itemPreview" pos="390,0" width="73" height="73" atlas="ItemIconAtlas" sprite="HardSkin" color="0,255,0" pivot="center" visible="{cvar(HardSkinSecondSkill_Temp:true;false;false)}" foregroundlayer="true"/>
						

					
						<sprite depth="4" name="itemPreview" pos="390,0" width="73" height="73" atlas="ItemIconAtlas" sprite="ExplodingVultures" color="0,255,0" pivot="center" visible="{cvar(ExplodingVulturesSecondSkill_Temp:true;false;false)}" foregroundlayer="true"/>
						<sprite depth="4" name="itemPreview" pos="390,0" width="73" height="73" atlas="ItemIconAtlas" sprite="GustingWind" color="0,255,0" pivot="center" visible="{cvar(GustingwindSecondSkill_Temp:true;false;false)}" foregroundlayer="true"/>
						<sprite depth="4" name="itemPreview" pos="390,0" width="73" height="73" atlas="ItemIconAtlas" sprite="Spawningvultures" color="0,255,0" pivot="center" visible="{cvar(SpawningvulturesSecondSkill_Temp:true;false;false)}" foregroundlayer="true"/>
						<sprite depth="4" name="itemPreview" pos="390,0" width="73" height="73" atlas="ItemIconAtlas" sprite="Quicksand" color="0,255,0" pivot="center" visible="{cvar(QuickSandSecondSkill_Temp:true;false;false)}" foregroundlayer="true"/>
						<sprite depth="4" name="itemPreview" pos="390,0" width="73" height="73" atlas="ItemIconAtlas" sprite="Entoumb" color="0,255,0" pivot="center" visible="{cvar(EntoumbSecondSkill_Temp:true;false;false)}" foregroundlayer="true"/>
						<sprite depth="4" name="itemPreview" pos="390,0" width="73" height="73" atlas="ItemIconAtlas" sprite="TalonStrike" color="0,255,0" pivot="center" visible="{cvar(TalonStrikeSecondSkill_Temp:true;false;false)}" foregroundlayer="true"/>
						<sprite depth="4" name="itemPreview" pos="390,0" width="73" height="73" atlas="ItemIconAtlas" sprite="sandstorm" color="0,255,0" pivot="center" visible="{cvar(SandStormSecondSkill_Temp:true;false;false)}" foregroundlayer="true"/>
						<sprite depth="4" name="itemPreview" pos="390,0" width="73" height="73" atlas="ItemIconAtlas" sprite="Exhaustion" color="0,255,0" pivot="center" visible="{cvar(ExhaustionSecondSkill_Temp:true;false;false)}" foregroundlayer="true"/>
						<sprite depth="4" name="itemPreview" pos="390,0" width="73" height="73" atlas="ItemIconAtlas" sprite="SlowingTotem" color="0,255,0" pivot="center" visible="{cvar(SlowingTotemSecondSkill_Temp:true;false;false)}" foregroundlayer="true"/>
						

					
						<sprite depth="4" name="itemPreview" pos="390,0" width="73" height="73" atlas="ItemIconAtlas" sprite="BearCharge" color="0,255,200" pivot="center" visible="{cvar(BearChargeSecondSkill_Temp:true;false;false)}" foregroundlayer="true"/>
						<sprite depth="4" name="itemPreview" pos="390,0" width="73" height="73" atlas="ItemIconAtlas" sprite="Splice" color="0,255,200" pivot="center" visible="{cvar(SpliceSecondSkill_Temp:true;false;false)}" foregroundlayer="true"/>
						<sprite depth="4" name="itemPreview" pos="390,0" width="73" height="73" atlas="ItemIconAtlas" sprite="Avalanche" color="{cvar(AWR)},{cvar(AWG)},{cvar(AWB)}" pivot="center" visible="{cvar(ArcticWinterSecondSkill_Temp:true;false;false)}" foregroundlayer="true"/>
						<sprite depth="4" name="itemPreview" pos="390,0" width="73" height="73" atlas="ItemIconAtlas" sprite="GroundStomp" color="0,255,200" pivot="center" visible="{cvar(GroundSlamSecondSkill_Temp:true;false;false)}" foregroundlayer="true"/>
						<sprite depth="4" name="itemPreview" pos="390,0" width="73" height="73" atlas="ItemIconAtlas" sprite="GrizzlyBite" color="0,255,200" pivot="center" visible="{cvar(GrizzlyBiteSecondSkill_Temp:true;false;false)}" foregroundlayer="true"/>
						<sprite depth="4" name="itemPreview" pos="390,0" width="73" height="73" atlas="ItemIconAtlas" sprite="Maul" color="0,255,200" pivot="center" visible="{cvar(MaulSecondSkill_Temp:true;false;false)}" foregroundlayer="true"/>
						<sprite depth="4" name="itemPreview" pos="390,0" width="73" height="73" atlas="ItemIconAtlas" sprite="PhysicalResistance" color="0,255,200" pivot="center" visible="{cvar(PhysicalResistanceSecondSkill_Temp:true;false;false)}" foregroundlayer="true"/>
						<sprite depth="4" name="itemPreview" pos="390,0" width="73" height="73" atlas="ItemIconAtlas" sprite="FireResistance" color="0,255,200" pivot="center" visible="{cvar(FireResistanceSecondSkill_Temp:true;false;false)}" foregroundlayer="true"/>
						<sprite depth="4" name="itemPreview" pos="390,0" width="73" height="73" atlas="ItemIconAtlas" sprite="territorial" color="0,255,200" pivot="center" visible="{cvar(territorialSecondSkill_Temp:true;false;false)}" foregroundlayer="true"/>
						
				</rect>

				<rect pos="0,0">

					
						<sprite depth="5" name="itemPreview" pos="472,0" width="80" height="80" atlas="ItemIconAtlas" sprite="SkillDisplay" color="{itemicontint}" pivot="center" visible="{cvar(SkillSlots_Temp:true;false;false)}" foregroundlayer="true"/>
					

					

					
						<sprite depth="4" name="itemPreview" pos="472,0" width="73" height="73" atlas="ItemIconAtlas" sprite="VineSnap" color="0,255,0" pivot="center" visible="{cvar(VineSnapThirdSkill_Temp:true;false;false)}" foregroundlayer="true"/>
						<sprite depth="4" name="itemPreview" pos="472,0" width="73" height="73" atlas="ItemIconAtlas" sprite="PoisonTouch" color="0,255,0" pivot="center" visible="{cvar(PoisonTouchThirdSkill_Temp:true;false;false)}" foregroundlayer="true"/>
						<sprite depth="4" name="itemPreview" pos="472,0" width="73" height="73" atlas="ItemIconAtlas" sprite="CallOfTheWolves" color="{cvar(COTWCooldownRed)},{cvar(COTWCooldownGreen)},{cvar(COTWCooldownBlue)}" pivot="center" visible="{cvar(CallOfTheWolvesThirdSkill_Temp:true;false;false)}" foregroundlayer="true"/>
						<sprite depth="4" name="itemPreview" pos="472,0" width="73" height="73" atlas="ItemIconAtlas" sprite="RageOfTheForest" color="0,255,0" pivot="center" visible="{cvar(RageOfTheForestThirdSkill_Temp:true;false;false)}" foregroundlayer="true"/>
						<sprite depth="4" name="itemPreview" pos="472,0" width="73" height="73" atlas="ItemIconAtlas" sprite="RampidSprouts" color="0,255,0" pivot="center" visible="{cvar(RampidSproutsThirdSkill_Temp:true;false;false)}" foregroundlayer="true"/>
						<sprite depth="4" name="itemPreview" pos="472,0" width="73" height="73" atlas="ItemIconAtlas" sprite="BuffAllies" color="0,255,0" pivot="center" visible="{cvar(BuffAlliesThirdSkill_Temp:true;false;false)}" foregroundlayer="true"/>
						<sprite depth="4" name="itemPreview" pos="472,0" width="73" height="73" atlas="ItemIconAtlas" sprite="HealingMist" color="0,255,0" pivot="center" visible="{cvar(HealingMistThirdSkill_Temp:true;false;false)}" foregroundlayer="true"/>
						<sprite depth="4" name="itemPreview" pos="472,0" width="73" height="73" atlas="ItemIconAtlas" sprite="AcidRain" color="0,255,0" pivot="center" visible="{cvar(AcidRainThirdSkill_Temp:true;false;false)}" foregroundlayer="true"/>
						<sprite depth="4" name="itemPreview" pos="472,0" width="73" height="73" atlas="ItemIconAtlas" sprite="HardSkin" color="0,255,0" pivot="center" visible="{cvar(HardSkinThirdSkill_Temp:true;false;false)}" foregroundlayer="true"/>
						

					
						<sprite depth="4" name="itemPreview" pos="472,0" width="73" height="73" atlas="ItemIconAtlas" sprite="ExplodingVultures" color="0,255,0" pivot="center" visible="{cvar(ExplodingVulturesThirdSkill_Temp:true;false;false)}" foregroundlayer="true"/>
						<sprite depth="4" name="itemPreview" pos="472,0" width="73" height="73" atlas="ItemIconAtlas" sprite="GustingWind" color="0,255,0" pivot="center" visible="{cvar(GustingwindThirdSkill_Temp:true;false;false)}" foregroundlayer="true"/>
						<sprite depth="4" name="itemPreview" pos="472,0" width="73" height="73" atlas="ItemIconAtlas" sprite="Spawningvultures" color="0,255,0" pivot="center" visible="{cvar(SpawningvulturesThirdSkill_Temp:true;false;false)}" foregroundlayer="true"/>
						<sprite depth="4" name="itemPreview" pos="472,0" width="73" height="73" atlas="ItemIconAtlas" sprite="Quicksand" color="0,255,0" pivot="center" visible="{cvar(QuickSandThirdSkill_Temp:true;false;false)}" foregroundlayer="true"/>
						<sprite depth="4" name="itemPreview" pos="472,0" width="73" height="73" atlas="ItemIconAtlas" sprite="Entoumb" color="0,255,0" pivot="center" visible="{cvar(EntoumbThirdSkill_Temp:true;false;false)}" foregroundlayer="true"/>
						<sprite depth="4" name="itemPreview" pos="472,0" width="73" height="73" atlas="ItemIconAtlas" sprite="TalonStrike" color="0,255,0" pivot="center" visible="{cvar(TalonStrikeThirdSkill_Temp:true;false;false)}" foregroundlayer="true"/>
						<sprite depth="4" name="itemPreview" pos="472,0" width="73" height="73" atlas="ItemIconAtlas" sprite="sandstorm" color="0,255,0" pivot="center" visible="{cvar(SandStormThirdSkill_Temp:true;false;false)}" foregroundlayer="true"/>
						<sprite depth="4" name="itemPreview" pos="472,0" width="73" height="73" atlas="ItemIconAtlas" sprite="Exhaustion" color="0,255,0" pivot="center" visible="{cvar(ExhaustionThirdSkill_Temp:true;false;false)}" foregroundlayer="true"/>
						<sprite depth="4" name="itemPreview" pos="472,0" width="73" height="73" atlas="ItemIconAtlas" sprite="SlowingTotem" color="0,255,0" pivot="center" visible="{cvar(SlowingTotemThirdSkill_Temp:true;false;false)}" foregroundlayer="true"/>
						

					
						<sprite depth="4" name="itemPreview" pos="472,0" width="73" height="73" atlas="ItemIconAtlas" sprite="BearCharge" color="0,255,200" pivot="center" visible="{cvar(BearChargeThirdSkill_Temp:true;false;false)}" foregroundlayer="true"/>
						<sprite depth="4" name="itemPreview" pos="472,0" width="73" height="73" atlas="ItemIconAtlas" sprite="Splice" color="0,255,200" pivot="center" visible="{cvar(SpliceThirdSkill_Temp:true;false;false)}" foregroundlayer="true"/>
						<sprite depth="4" name="itemPreview" pos="472,0" width="73" height="73" atlas="ItemIconAtlas" sprite="Avalanche" color="{cvar(AWR)},{cvar(AWG)},{cvar(AWB)}" pivot="center" visible="{cvar(ArcticWinterThirdSkill_Temp:true;false;false)}" foregroundlayer="true"/>
						<sprite depth="4" name="itemPreview" pos="472,0" width="73" height="73" atlas="ItemIconAtlas" sprite="GroundStomp" color="0,255,200" pivot="center" visible="{cvar(GroundSlamThirdSkill_Temp:true;false;false)}" foregroundlayer="true"/>
						<sprite depth="4" name="itemPreview" pos="472,0" width="73" height="73" atlas="ItemIconAtlas" sprite="GrizzlyBite" color="0,255,200" pivot="center" visible="{cvar(GrizzlyBiteThirdSkill_Temp:true;false;false)}" foregroundlayer="true"/>
						<sprite depth="4" name="itemPreview" pos="472,0" width="73" height="73" atlas="ItemIconAtlas" sprite="Maul" color="0,255,200" pivot="center" visible="{cvar(MaulThirdSkill_Temp:true;false;false)}" foregroundlayer="true"/>
						<sprite depth="4" name="itemPreview" pos="472,0" width="73" height="73" atlas="ItemIconAtlas" sprite="PhysicalResistance" color="0,255,200" pivot="center" visible="{cvar(PhysicalResistanceThirdSkill_Temp:true;false;false)}" foregroundlayer="true"/>
						<sprite depth="4" name="itemPreview" pos="472,0" width="73" height="73" atlas="ItemIconAtlas" sprite="FireResistance" color="0,255,200" pivot="center" visible="{cvar(FireResistanceThirdSkill_Temp:true;false;false)}" foregroundlayer="true"/>
						<sprite depth="4" name="itemPreview" pos="472,0" width="73" height="73" atlas="ItemIconAtlas" sprite="territorial" color="0,255,200" pivot="center" visible="{cvar(territorialThirdSkill_Temp:true;false;false)}" foregroundlayer="true"/>
				</rect>	
			</rect>
		</window>
	
		<window name="BossSpawnIndicator" width="360" height="60" anchor="CenterBottom" pos="0,5" controller="ToolbeltWindow" cursor_area="false">
		

				
			<rect pos="0,0" >

				<rect pos="425,50">
					<sprite depth="1" name="windowicon" style="icon32px" pos="0,0" pivot="center" justify="center" width="78" height="78" sprite="ui_game_filled_circle" color="[darkestGrey]"/>
					<sprite depth="2" name="windowicon" style="icon32px" pos="0,0" pivot="center" justify="center" width="78" height="78" sprite="ui_game_filled_circle" color="0,0,0,150"/>
				</rect>
				

				<rect pos="425,50">
					<sprite depth="-1" height="88" width="88" name="background" pos="0,0" sprite="ui_game_filled_circle" color="255,0,255,500" justify="center" pivot="center" type="filled" fill="{cvar(BozwardoSpawnJuiceMaxDisplayPerc2)}" filldirection="radial360" visible="{cvar(BozwardoDisplay:true;false;false)}"/>
					<sprite depth="4" height="83" width="83" name="background" pos="0,0" sprite="ui_game_filled_circle" color="0,150,40,175" pivot="center" type="filled" fill="{cvar(BozwardoSpawnJuiceMaxDisplayPerc)}" filldirection="vertical" visible="{cvar(BozwardoDisplay:true;false;false)}"/>
					<sprite depth="3" name="windowicon" style="icon32px" pos="-2,0" pivot="center" justify="center" width="60" height="60" fillcenter="false" sprite="ui_game_symbol_zombie" color="0,150,40,175" visible="{cvar(BozwardoDisplay:true;false;false)}"/>
					<sprite depth="0" name="windowicon" style="icon32px" pos="0,0" pivot="center" justify="center" width="83" height="83" fillcenter="false" sprite="ui_game_filled_circle" color="0,150,40,255" visible="{cvar(BozwardoDisplay:true;false;false)}"/>
				</rect>


				<rect pos="425,50">
					<sprite depth="1" name="windowicon" style="icon32px" pos="0,0" pivot="center" justify="center" width="78" height="78" sprite="ui_game_filled_circle" color="[darkestGrey]"/>
					<sprite depth="2" name="windowicon" style="icon32px" pos="0,0" pivot="center" justify="center" width="78" height="78" sprite="ui_game_filled_circle" color="0,0,0,150"/>
					<sprite depth="-1" height="88" width="88" name="background" pos="0,0" sprite="ui_game_filled_circle" color="255,0,255,500" justify="center" pivot="center" type="filled" fill="{cvar(R3dHotSpawnJuiceMaxDisplayPerc2)}" filldirection="radial360" visible="{cvar(R3dHotDisplay:true;false;false)}"/>
					<sprite depth="4" height="83" width="83" name="background" pos="0,0" sprite="ui_game_filled_circle" color="170,6,35" pivot="center" type="filled" fill="{cvar(R3dHotSpawnJuiceMaxDisplayPerc)}" filldirection="vertical" visible="{cvar(R3dHotDisplay:true;false;false)}"/>
					<sprite depth="3" name="windowicon" style="icon32px" pos="-2,0" pivot="center" justify="center" width="60" height="60" fillcenter="false" sprite="ui_game_symbol_zombie" color="249,11,53" visible="{cvar(R3dHotDisplay:true;false;false)}"/>
					<sprite depth="0" name="windowicon" style="icon32px" pos="0,0" pivot="center" justify="center" width="83" height="83" fillcenter="false" sprite="ui_game_filled_circle" color="249,11,53" visible="{cvar(R3dHotDisplay:true;false;false)}"/>
				</rect>
				

				<rect pos="425,50">
					<sprite depth="-1" height="88" width="88" name="background" pos="0,0" sprite="ui_game_filled_circle" color="255,0,255,500" justify="center" pivot="center" type="filled" fill="{cvar(RevekaSpawnJuiceMaxDisplayPerc2)}" filldirection="radial360" visible="{cvar(RevekaDisplay:true;false;false)}"/>
					<sprite depth="3" height="83" width="83" name="background" pos="0,0" sprite="ui_game_filled_circle" color="255,147,0,175" pivot="center" type="filled" fill="{cvar(RevekaSpawnJuiceMaxDisplayPerc)}" filldirection="vertical" visible="{cvar(RevekaDisplay:true;false;false)}"/>
					<sprite depth="4" name="windowicon" style="icon32px" pos="-2,0" pivot="center" justify="center" width="60" height="60" fillcenter="false" sprite="ui_game_symbol_zombie" color="255,147,0,175" visible="{cvar(RevekaDisplay:true;false;false)}"/>
					<sprite depth="0" name="windowicon" style="icon32px" pos="0,0" pivot="center" justify="center" width="83" height="83" fillcenter="false" sprite="ui_game_filled_circle" color="255,147,0,175" visible="{cvar(RevekaDisplay:true;false;false)}"/>
				</rect>


				<rect pos="425,50">
					<sprite depth="-1" height="88" width="88" name="background" pos="0,0" sprite="ui_game_filled_circle" color="255,0,255,500" justify="center" pivot="center" type="filled" fill="{cvar(KarnageKimSpawnJuiceMaxDisplayPerc2)}" filldirection="radial360" visible="{cvar(KarnageKimDisplay:true;false;false)}"/>
					<sprite depth="3" height="83" width="83" name="background" pos="0,0" sprite="ui_game_filled_circle" color="255,147,0,175" pivot="center" type="filled" fill="{cvar(KarnageKimSpawnJuiceMaxDisplayPerc)}" filldirection="vertical" visible="{cvar(KarnageKimDisplay:true;false;false)}"/>
					<sprite depth="4" name="windowicon" style="icon32px" pos="-2,0" pivot="center" justify="center" width="60" height="60" fillcenter="false" sprite="ui_game_symbol_zombie" color="255,147,0,175" visible="{cvar(KarnageKimaDisplay:true;false;false)}"/>
					<sprite depth="0" name="windowicon" style="icon32px" pos="0,0" pivot="center" justify="center" width="83" height="83" fillcenter="false" sprite="ui_game_filled_circle" color="255,147,0,175" visible="{cvar(KarnageKimDisplay:true;false;false)}"/>
				</rect>


				<rect pos="425,50">
					<sprite depth="-1" height="88" width="88" name="background" pos="0,0" sprite="ui_game_filled_circle" color="255,0,255,500" justify="center" pivot="center" type="filled" fill="{cvar(CrazedCannonSpawnJuiceMaxDisplayPerc2)}" filldirection="radial360" visible="{cvar(CrazedCannonDisplay:true;false;false)}"/>
					<sprite depth="3" height="83" width="83" name="background" pos="0,0" sprite="ui_game_filled_circle" color="255,147,0,175" pivot="center" type="filled" fill="{cvar(CrazedCannonSpawnJuiceMaxDisplayPerc)}" filldirection="vertical" visible="{cvar(CrazedCannonDisplay:true;false;false)}"/>
					<sprite depth="4" name="windowicon" style="icon32px" pos="-2,0" pivot="center" justify="center" width="60" height="60" fillcenter="false" sprite="ui_game_symbol_zombie" color="255,147,0,175" visible="{cvar(CrazedCannonDisplay:true;false;false)}"/>
					<sprite depth="0" name="windowicon" style="icon32px" pos="0,0" pivot="center" justify="center" width="83" height="83" fillcenter="false" sprite="ui_game_filled_circle" color="255,147,0,175" visible="{cvar(CrazedCannonDisplay:true;false;false)}"/>
				</rect>
			</rect>
			
		
			
		</window>
	
	</append>
-->
</configs>